<?xml version="1.0" encoding="utf-8" ?><dwsync><file name="education-bg.jpg" server="ftp.mattblair.co.uk" local="3462881264" remote="3505242780" Dst="-1" /><file name="infoman-bg.jpg" server="ftp.mattblair.co.uk" local="3462883848" remote="3505242780" Dst="-1" /><file name="archives-sector.jpg" server="ftp.mattblair.co.uk" local="3472732660" remote="3505242780" Dst="-1" /><file name="bg-banner-newsletter.png" server="ftp.mattblair.co.uk" local="3501754606" remote="3505242780" Dst="-1" /><file name="20131002_blog-bg.jpg" server="ftp.mattblair.co.uk" local="3463464908" remote="3505242900" Dst="-1" /><file name="advisory-council2-th.jpg" server="ftp.mattblair.co.uk" local="3383821348" remote="3505242900" Dst="-1" /><file name="adm-101-7-8-th.jpg" server="ftp.mattblair.co.uk" local="3368614502" remote="3505242900" Dst="-1" /><file name="archive-sector-update-th.jpg" server="ftp.mattblair.co.uk" local="3343139532" remote="3505242900" Dst="-1" /><file name="audio-video-icon.gif" server="ftp.mattblair.co.uk" local="3445866950" remote="3505242900" Dst="-1" /><file name="battle-of-towton-copyright-graham-turner-studio88.jpg" server="ftp.mattblair.co.uk" local="3384336360" remote="3505242900" Dst="-1" /><file name="bess-hardwick-thumb.jpg" server="ftp.mattblair.co.uk" local="3436516718" remote="3505242900" Dst="-1" /><file name="blog-bg.jpg" server="ftp.mattblair.co.uk" local="3486366094" remote="3505242900" Dst="-1" /><file name="blog-thumb.jpg" server="ftp.mattblair.co.uk" local="3411998102" remote="3505242900" Dst="-1" /><file name="bookshop-bg.jpg" server="ftp.mattblair.co.uk" local="3502194104" remote="3505242900" Dst="-1" /><file name="bookshop-bg-old.jpg" server="ftp.mattblair.co.uk" local="3463135762" remote="3505242900" Dst="-1" /><file name="bookshop-bg-old-old.jpg" server="ftp.mattblair.co.uk" local="3484547210" remote="3505242900" Dst="-1" /><file name="census-1891-th.jpg" server="ftp.mattblair.co.uk" local="3363342258" remote="3505242900" Dst="-1" /><file name="churchill-thumb.jpg" server="ftp.mattblair.co.uk" local="3373366716" remote="3505242900" Dst="-1" /><file name="co-956-99-1927-1933.jpg" server="ftp.mattblair.co.uk" local="3462090274" remote="3505242900" Dst="-1" /><file name="community-bg.jpg" server="ftp.mattblair.co.uk" local="3472553064" remote="3505242900" Dst="-1" /><file name="copy1-494-suffragettes-annie-kenny-christabel-pankhurst-1906-th.jpg" server="ftp.mattblair.co.uk" local="3404724450" remote="3505242900" Dst="-1" /><file name="copy-1-228-98-whitstable-1905.jpg" server="ftp.mattblair.co.uk" local="3462090406" remote="3505242900" Dst="-1" /><file name="data-55x55.jpg" server="ftp.mattblair.co.uk" local="3394626054" remote="3505242900" Dst="-1" /><file name="documents-in-library-th.jpg" server="ftp.mattblair.co.uk" local="3402042288" remote="3505242900" Dst="-1" /><file name="dot-grey.png" server="ftp.mattblair.co.uk" local="3459939488" remote="3505242900" Dst="-1" /><file name="education-banner2.jpg" server="ftp.mattblair.co.uk" local="3343048038" remote="3505242900" Dst="-1" /><file name="education-banner.jpg" server="ftp.mattblair.co.uk" local="3341928770" remote="3505242900" Dst="-1" /><file name="education-banner5.jpg" server="ftp.mattblair.co.uk" local="3343121906" remote="3505242900" Dst="-1" /><file name="education-banner3.jpg" server="ftp.mattblair.co.uk" local="3343048700" remote="3505242900" Dst="-1" /><file name="education-banner4.jpg" server="ftp.mattblair.co.uk" local="3343122386" remote="3505242900" Dst="-1" /><file name="enewsletter-bg.jpg" server="ftp.mattblair.co.uk" local="3462090594" remote="3505242900" Dst="-1" /><file name="events-item-1.jpg" server="ftp.mattblair.co.uk" local="3463393310" remote="3505242900" Dst="-1" /><file name="events-item-second-big-idea-1.jpg" server="ftp.mattblair.co.uk" local="3463647226" remote="3505242960" Dst="-1" /><file name="fco-93-614-front-cover-thumb.jpg" server="ftp.mattblair.co.uk" local="3415776532" remote="3505242960" Dst="-1" /><file name="history-of-secret-intelligence-service-book-th.jpg" server="ftp.mattblair.co.uk" local="3367997724" remote="3505242960" Dst="-1" /><file name="ho144-407-b23729-th.jpg" server="ftp.mattblair.co.uk" local="3415776524" remote="3505242960" Dst="-1" /><file name="im-banner.jpg" server="ftp.mattblair.co.uk" local="3341929076" remote="3505242960" Dst="-1" /><file name="im-banner2.jpg" server="ftp.mattblair.co.uk" local="3343122186" remote="3505242960" Dst="-1" /><file name="im-banner3.jpg" server="ftp.mattblair.co.uk" local="3343122472" remote="3505242960" Dst="-1" /><file name="imagelibrary-bg.jpg" server="ftp.mattblair.co.uk" local="3462090570" remote="3505242960" Dst="-1" /><file name="image-library2.jpg" server="ftp.mattblair.co.uk" local="3384247396" remote="3505242960" Dst="-1" /><file name="looted-art-th.jpg" server="ftp.mattblair.co.uk" local="3387448920" remote="3505242960" Dst="-1" /><file name="inf-3-1738.jpg" server="ftp.mattblair.co.uk" local="3462090370" remote="3505242960" Dst="-1" /><file name="map-location-the-national-archives.jpg" server="ftp.mattblair.co.uk" local="3474892570" remote="3505242960" Dst="-1" /><file name="menu-centenary-100.gif" server="ftp.mattblair.co.uk" local="3471873688" remote="3505242960" Dst="-1" /><file name="media-bg.jpg" server="ftp.mattblair.co.uk" local="3486019380" remote="3505242960" Dst="-1" /><file name="menu-first-world-war-b.jpg" server="ftp.mattblair.co.uk" local="3471945192" remote="3505242960" Dst="-1" /><file name="mepo35-2-9-th.jpg" server="ftp.mattblair.co.uk" local="3349960804" remote="3505242960" Dst="-1" /><file name="nceeney-th.jpg" server="ftp.mattblair.co.uk" local="3343139578" remote="3505242960" Dst="-1" /><file name="menu-first-world-war.jpg" server="ftp.mattblair.co.uk" local="3467031340" remote="3505242960" Dst="-1" /><file name="news-item-1.jpg" server="ftp.mattblair.co.uk" local="3463389850" remote="3505242960" Dst="-1" /><file name="old-news-item-1.jpg" server="ftp.mattblair.co.uk" local="3463130862" remote="3505242960" Dst="-1" /><file name="news-item-878.jpg" server="ftp.mattblair.co.uk" local="3463633580" remote="3505242960" Dst="-1" /><file name="partition-group-th.jpg" server="ftp.mattblair.co.uk" local="3401863644" remote="3505243020" Dst="-1" /><file name="patagonia.jpg" server="ftp.mattblair.co.uk" local="3346157144" remote="3505243020" Dst="-1" /><file name="placeholder.gif" server="ftp.mattblair.co.uk" local="3343053542" remote="3505243020" Dst="-1" /><file name="queens-award-2011-th.jpg" server="ftp.mattblair.co.uk" local="3399274782" remote="3505243020" Dst="-1" /><file name="pronom-data-tube.jpg" server="ftp.mattblair.co.uk" local="3393498488" remote="3505243020" Dst="-1" /><file name="record-stacks.jpg" server="ftp.mattblair.co.uk" local="3381921020" remote="3505243020" Dst="-1" /><file name="records-banner.jpg" server="ftp.mattblair.co.uk" local="3343129028" remote="3505243020" Dst="-1" /><file name="records-banner2.jpg" server="ftp.mattblair.co.uk" local="3343122358" remote="3505243020" Dst="-1" /><file name="records-banner3.jpg" server="ftp.mattblair.co.uk" local="3343122444" remote="3505243020" Dst="-1" /><file name="prem13-2412-010-th.jpg" server="ftp.mattblair.co.uk" local="3368513628" remote="3505243020" Dst="-1" /><file name="records-banner4.jpg" server="ftp.mattblair.co.uk" local="3343122140" remote="3505243020" Dst="-1" /><file name="rtr-thumb.jpg" server="ftp.mattblair.co.uk" local="3441194820" remote="3505243020" Dst="-1" /><file name="records-th.jpg" server="ftp.mattblair.co.uk" local="3343822860" remote="3505243020" Dst="-1" /><file name="rupert-brooke-th.jpg" server="ftp.mattblair.co.uk" local="3372313032" remote="3505243020" Dst="-1" /><file name="sp54-25-71-th.jpg" server="ftp.mattblair.co.uk" local="3343139460" remote="3505243020" Dst="-1" /><file name="t70-175-slavery-1680-1688-th.jpg" server="ftp.mattblair.co.uk" local="3367997782" remote="3505243020" Dst="-1" /><file name="temporary-survey-picture.jpg" server="ftp.mattblair.co.uk" local="3394616906" remote="3505243020" Dst="-1" /><file name="th-1911-census.jpg" server="ftp.mattblair.co.uk" local="3408610914" remote="3505243020" Dst="-1" /><file name="th-1939-prestatyn-holiday-camp-rail1057-2736.jpg" server="ftp.mattblair.co.uk" local="3432801388" remote="3505243020" Dst="-1" /><file name="th-50-pence.jpg" server="ftp.mattblair.co.uk" local="3380614704" remote="3505243020" Dst="-1" /><file name="th-aac.jpg" server="ftp.mattblair.co.uk" local="3395730436" remote="3505243020" Dst="-1" /><file name="th-academic-55px.jpg" server="ftp.mattblair.co.uk" local="3349872918" remote="3505243020" Dst="-1" /><file name="th-ace-logo.jpg" server="ftp.mattblair.co.uk" local="3417499096" remote="3505243020" Dst="-1" /><file name="th-adm-202-903-3.jpg" server="ftp.mattblair.co.uk" local="3438852388" remote="3505243020" Dst="-1" /><file name="th-adm-55-55px.jpg" server="ftp.mattblair.co.uk" local="3343139390" remote="3505243020" Dst="-1" /><file name="th-adm101-139-3-f36-leg-in-splint.jpg" server="ftp.mattblair.co.uk" local="3372854836" remote="3505243020" Dst="-1" /><file name="th-advert-draft-1.jpg" server="ftp.mattblair.co.uk" local="3391590280" remote="3505243020" Dst="-1" /><file name="th-agreement-on-cooperation.jpg" server="ftp.mattblair.co.uk" local="3441976626" remote="3505243020" Dst="-1" /><file name="th-albert.jpg" server="ftp.mattblair.co.uk" local="3350993174" remote="3505243020" Dst="-1" /><file name="th-alert.gif" server="ftp.mattblair.co.uk" local="3343912732" remote="3505243020" Dst="-1" /><file name="th-alert.jpg" server="ftp.mattblair.co.uk" local="3349418008" remote="3505243020" Dst="-1" /><file name="th-alert_rdax_55x55.jpg" server="ftp.mattblair.co.uk" local="3343975170" remote="3505243020" Dst="-1" /><file name="th-ancestors-55px.jpg" server="ftp.mattblair.co.uk" local="3347880412" remote="3505243020" Dst="-1" /><file name="th-ancestorsmag-55px.jpg" server="ftp.mattblair.co.uk" local="3350890898" remote="3505243020" Dst="-1" /><file name="th-annual-report-10-11.jpg" server="ftp.mattblair.co.uk" local="3391755222" remote="3505243020" Dst="-1" /><file name="th-annual-report-55px.jpg" server="ftp.mattblair.co.uk" local="3362034310" remote="3505243020" Dst="-1" /><file name="th-appg-5dec-2011.jpg" server="ftp.mattblair.co.uk" local="3406196690" remote="3505243020" Dst="-1" /><file name="th-archive-leadership.jpg" server="ftp.mattblair.co.uk" local="3400482838" remote="3505243020" Dst="-1" /><file name="th-appsi-logo.jpg" server="ftp.mattblair.co.uk" local="3388476094" remote="3505243020" Dst="-1" /><file name="th-archives-sector-screensh.jpg" server="ftp.mattblair.co.uk" local="3416379716" remote="3505243020" Dst="-1" /><file name="th-archives-sector-screensh.png" server="ftp.mattblair.co.uk" local="3416379906" remote="3505243020" Dst="-1" /><file name="th-archiving-arts-news.jpg" server="ftp.mattblair.co.uk" local="3458112160" remote="3505243020" Dst="-1" /><file name="th-armistice11-11-11.jpg" server="ftp.mattblair.co.uk" local="3403850870" remote="3505243020" Dst="-1" /><file name="th-australasia-news.jpg" server="ftp.mattblair.co.uk" local="3441714420" remote="3505243020" Dst="-1" /><file name="th-bbc-domesday-logo.jpg" server="ftp.mattblair.co.uk" local="3388037362" remote="3505243020" Dst="-1" /><file name="th-battle-of-towton-copyright-graham-turner-studio88.jpg" server="ftp.mattblair.co.uk" local="3384403370" remote="3505243020" Dst="-1" /><file name="th-bbc-vid-55px.jpg" server="ftp.mattblair.co.uk" local="3345805786" remote="3505243020" Dst="-1" /><file name="th-bmd-at-sea-55px.jpg" server="ftp.mattblair.co.uk" local="3345104558" remote="3505243020" Dst="-1" /><file name="th-bookshop-jan-sale.jpg" server="ftp.mattblair.co.uk" local="3408438024" remote="3505243020" Dst="-1" /><file name="th-bookshop.jpg" server="ftp.mattblair.co.uk" local="3462785852" remote="3505243020" Dst="-1" /><file name="th-brendan-behan.jpg" server="ftp.mattblair.co.uk" local="3350555502" remote="3505243020" Dst="-1" /><file name="th-budgetbox-55px.jpg" server="ftp.mattblair.co.uk" local="3359720198" remote="3505243020" Dst="-1" /><file name="th-catalogue.jpg" server="ftp.mattblair.co.uk" local="3397199884" remote="3505243020" Dst="-1" /><file name="th-celebrating-census-conference.jpg" server="ftp.mattblair.co.uk" local="3393228880" remote="3505243020" Dst="-1" /><file name="th-cataloguingimage.jpg" server="ftp.mattblair.co.uk" local="3347974662" remote="3505243020" Dst="-1" /><file name="th-chelsea-pensioners-55px.jpg" server="ftp.mattblair.co.uk" local="3372666358" remote="3505243020" Dst="-1" /><file name="th-census-55px.jpg" server="ftp.mattblair.co.uk" local="3347257116" remote="3505243020" Dst="-1" /><file name="th-chelseapensioners-55px.jpg" server="ftp.mattblair.co.uk" local="3356671868" remote="3505243020" Dst="-1" /><file name="th-chelseapensioners.jpg" server="ftp.mattblair.co.uk" local="3351580562" remote="3505243020" Dst="-1" /><file name="th-cheshire-salt-mine-55px.jpg" server="ftp.mattblair.co.uk" local="3364295588" remote="3505243020" Dst="-1" /><file name="th-christmas-showcase.jpg" server="ftp.mattblair.co.uk" local="3405665924" remote="3505243020" Dst="-1" /><file name="th-communism-papers.jpg" server="ftp.mattblair.co.uk" local="3433335324" remote="3505243020" Dst="-1" /><file name="th-copy1-218-230-schools.jpg" server="ftp.mattblair.co.uk" local="3390825546" remote="3505243020" Dst="-1" /><file name="th-connected-histories-screenshot.jpg" server="ftp.mattblair.co.uk" local="3384838134" remote="3505243020" Dst="-1" /><file name="th-copy1-381-f350-queen-victoria-smiling-1887.jpg" server="ftp.mattblair.co.uk" local="3400573014" remote="3505243020" Dst="-1" /><file name="th-copy1-362-f125.jpg" server="ftp.mattblair.co.uk" local="3389691352" remote="3505243020" Dst="-1" /><file name="th-criminal.jpg" server="ftp.mattblair.co.uk" local="3396413252" remote="3505243020" Dst="-1" /><file name="th-data-disc-55px.jpg" server="ftp.mattblair.co.uk" local="3349785638" remote="3505243020" Dst="-1" /><file name="th-dc-55px.jpg" server="ftp.mattblair.co.uk" local="3352978314" remote="3505243020" Dst="-1" /><file name="th-data-55px.jpg" server="ftp.mattblair.co.uk" local="3346917642" remote="3505243020" Dst="-1" /><file name="th-discover-local-heroes-55px.jpg" server="ftp.mattblair.co.uk" local="3367471782" remote="3505243020" Dst="-1" /><file name="th-discovery-screenshot.png" server="ftp.mattblair.co.uk" local="3416380042" remote="3505243020" Dst="-1" /><file name="th-diversity-duleep-singh.jpg" server="ftp.mattblair.co.uk" local="3403078066" remote="3505243020" Dst="-1" /><file name="th-document-rolls-in-box.jpg" server="ftp.mattblair.co.uk" local="3406017172" remote="3505243020" Dst="-1" /><file name="th-documents.jpg" server="ftp.mattblair.co.uk" local="3397736600" remote="3505243020" Dst="-1" /><file name="th-dol-haiti-55px.jpg" server="ftp.mattblair.co.uk" local="3352956116" remote="3505243020" Dst="-1" /><file name="th-domesday-55px.jpg" server="ftp.mattblair.co.uk" local="3363864204" remote="3505243020" Dst="-1" /><file name="th-domesday-e3-2-1.jpg" server="ftp.mattblair.co.uk" local="3395979356" remote="3505243080" Dst="-1" /><file name="th-domesday-maps-55px.jpg" server="ftp.mattblair.co.uk" local="3369635826" remote="3505243080" Dst="-1" /><file name="th-dpc-55px.jpg" server="ftp.mattblair.co.uk" local="3374479894" remote="3505243080" Dst="-1" /><file name="th-dorset-manorial-documents.jpg" server="ftp.mattblair.co.uk" local="3402475854" remote="3505243080" Dst="-1" /><file name="th-dpc-award-team.jpg" server="ftp.mattblair.co.uk" local="3432884422" remote="3505243080" Dst="-1" /><file name="th-education-masters-55px.jpg" server="ftp.mattblair.co.uk" local="3348814160" remote="3505243080" Dst="-1" /><file name="th-ed-award.jpg" server="ftp.mattblair.co.uk" local="3392813338" remote="3505243080" Dst="-1" /><file name="th-edible-archives.jpg" server="ftp.mattblair.co.uk" local="3406613546" remote="3505243080" Dst="-1" /><file name="th-eileen-mary-nearne-55px.jpg" server="ftp.mattblair.co.uk" local="3371115632" remote="3505243080" Dst="-1" /><file name="th-endangered-archives-bl.jpg" server="ftp.mattblair.co.uk" local="3430898430" remote="3505243080" Dst="-1" /><file name="th-energy.jpg" server="ftp.mattblair.co.uk" local="3438322542" remote="3505243080" Dst="-1" /><file name="th-euro-archive-55px.jpg" server="ftp.mattblair.co.uk" local="3351751936" remote="3505243080" Dst="-1" /><file name="th-fam-hist-fair-55px.jpg" server="ftp.mattblair.co.uk" local="3366958502" remote="3505243080" Dst="-1" /><file name="th-fco55-351.jpg" server="ftp.mattblair.co.uk" local="3390208918" remote="3505243080" Dst="-1" /><file name="th-file-release-aug-10-55px.jpg" server="ftp.mattblair.co.uk" local="3365502920" remote="3505243080" Dst="-1" /><file name="th-finding-archives.jpg" server="ftp.mattblair.co.uk" local="3401092128" remote="3505243080" Dst="-1" /><file name="th-festival-of-britain.jpg" server="ftp.mattblair.co.uk" local="3385533996" remote="3505243080" Dst="-1" /><file name="th-foi-55px.jpg" server="ftp.mattblair.co.uk" local="3358508342" remote="3505243080" Dst="-1" /><file name="th-fleur-de-lys-55px.jpg" server="ftp.mattblair.co.uk" local="3344427514" remote="3505243080" Dst="-1" /><file name="th-football.jpg" server="ftp.mattblair.co.uk" local="3359355670" remote="3505243080" Dst="-1" /><file name="th-for-the-record-for-good-image.jpg" server="ftp.mattblair.co.uk" local="3384176864" remote="3505243080" Dst="-1" /><file name="th-free1911.jpg" server="ftp.mattblair.co.uk" local="3387273578" remote="3505243080" Dst="-1" /><file name="th-friends-of-the-national-archives.jpg" server="ftp.mattblair.co.uk" local="3382686802" remote="3505243080" Dst="-1" /><file name="th-giraffes.jpg" server="ftp.mattblair.co.uk" local="3380100258" remote="3505243080" Dst="-1" /><file name="th-golden-rail-55px.jpg" server="ftp.mattblair.co.uk" local="3361535656" remote="3505243080" Dst="-1" /><file name="th-gro-55px.jpg" server="ftp.mattblair.co.uk" local="3350890872" remote="3505243080" Dst="-1" /><file name="th-guy-fawkes-55px.jpg" server="ftp.mattblair.co.uk" local="3371811696" remote="3505243080" Dst="-1" /><file name="th-handwritten-document.jpg" server="ftp.mattblair.co.uk" local="3379596810" remote="3505243080" Dst="-1" /><file name="th-ho45-24514-55-oscar-wildes-first-petition-to-the-home-sec.jpg" server="ftp.mattblair.co.uk" local="3442482488" remote="3505243080" Dst="-1" /><file name="th-hlf-logo.jpg" server="ftp.mattblair.co.uk" local="3386656500" remote="3505243080" Dst="-1" /><file name="th-hidden-lives-revealed.jpg" server="ftp.mattblair.co.uk" local="3427186602" remote="3505243080" Dst="-1" /><file name="th-homepage.jpg" server="ftp.mattblair.co.uk" local="3391166290" remote="3505243080" Dst="-1" /><file name="th-hs9-1089-2-1-eileen-mary-nearne.jpg" server="ftp.mattblair.co.uk" local="3410436162" remote="3505243080" Dst="-1" /><file name="th-hung-parliament-55px.jpg" server="ftp.mattblair.co.uk" local="3357212878" remote="3505243080" Dst="-1" /><file name="th-inf1-244-raf-airmen2.jpg" server="ftp.mattblair.co.uk" local="3410340678" remote="3505243080" Dst="-1" /><file name="th-infoman-55px.jpg" server="ftp.mattblair.co.uk" local="3356589790" remote="3505243080" Dst="-1" /><file name="th-john-vassall-national-portrait-gallery-6552.jpg" server="ftp.mattblair.co.uk" local="3433244170" remote="3505243080" Dst="-1" /><file name="th-keyboard-55px.jpg" server="ftp.mattblair.co.uk" local="3375101944" remote="3505243080" Dst="-1" /><file name="th-kingspeech-mfq1-525.jpg" server="ftp.mattblair.co.uk" local="3381380546" remote="3505243080" Dst="-1" /><file name="th-kobo-glo.jpg" server="ftp.mattblair.co.uk" local="3436351556" remote="3505243080" Dst="-1" /><file name="th-kv2-3538-angel-alcazar-de-velasco.jpg" server="ftp.mattblair.co.uk" local="3397020912" remote="3505243080" Dst="-1" /><file name="th-labs-55px.jpg" server="ftp.mattblair.co.uk" local="3359624582" remote="3505243080" Dst="-1" /><file name="th-labs-discovery.jpg" server="ftp.mattblair.co.uk" local="3386141448" remote="3505243080" Dst="-1" /><file name="th-laptop-55px.jpg" server="ftp.mattblair.co.uk" local="3343139498" remote="3505243080" Dst="-1" /><file name="th-legislation-logo.jpg" server="ftp.mattblair.co.uk" local="3385032700" remote="3505243080" Dst="-1" /><file name="th-library-shelves.jpg" server="ftp.mattblair.co.uk" local="3394782828" remote="3505243080" Dst="-1" /><file name="th-lisa-jardine.jpg" server="ftp.mattblair.co.uk" local="3405679102" remote="3505243080" Dst="-1" /><file name="th-live-chat-icon.gif" server="ftp.mattblair.co.uk" local="3431502998" remote="3505243080" Dst="-1" /><file name="th-local-archives.jpg" server="ftp.mattblair.co.uk" local="3394431232" remote="3505243080" Dst="-1" /><file name="th-london-gazette.jpg" server="ftp.mattblair.co.uk" local="3435323904" remote="3505243080" Dst="-1" /><file name="th-manor-of-eakring.jpg" server="ftp.mattblair.co.uk" local="3397711646" remote="3505243080" Dst="-1" /><file name="th-manorial-documents.jpg" server="ftp.mattblair.co.uk" local="3432530224" remote="3505243080" Dst="-1" /><file name="th-manorial-record.jpg" server="ftp.mattblair.co.uk" local="3415104308" remote="3505243080" Dst="-1" /><file name="th-mental-health-registers-55px.jpg" server="ftp.mattblair.co.uk" local="3358505394" remote="3505243080" Dst="-1" /><file name="th-mervyn-peake-art.jpg" server="ftp.mattblair.co.uk" local="3392107168" remote="3505243080" Dst="-1" /><file name="th-merchant-navy.jpg" server="ftp.mattblair.co.uk" local="3397736678" remote="3505243080" Dst="-1" /><file name="th-microfilm-55px.jpg" server="ftp.mattblair.co.uk" local="3348229390" remote="3505243080" Dst="-1" /><file name="th-moj-55px.jpg" server="ftp.mattblair.co.uk" local="3356671424" remote="3505243080" Dst="-1" /><file name="th-militia.jpg" server="ftp.mattblair.co.uk" local="3391682956" remote="3505243080" Dst="-1" /><file name="th-nara-logo.jpg" server="ftp.mattblair.co.uk" local="3374480734" remote="3505243080" Dst="-1" /><file name="th-moj-crest-55px.jpg" server="ftp.mattblair.co.uk" local="3363237956" remote="3505243080" Dst="-1" /><file name="th-national-society-news-ed-228-6.jpg" server="ftp.mattblair.co.uk" local="3401360804" remote="3505243080" Dst="-1" /><file name="th-navy-55px.jpg" server="ftp.mattblair.co.uk" local="3369897540" remote="3505243080" Dst="-1" /><file name="th-ndad-55px.jpg" server="ftp.mattblair.co.uk" local="3352183954" remote="3505243080" Dst="-1" /><file name="th-new-releases-55px.jpg" server="ftp.mattblair.co.uk" local="3344429312" remote="3505243080" Dst="-1" /><file name="th-nightingale-55px.jpg" server="ftp.mattblair.co.uk" local="3348230004" remote="3505243080" Dst="-1" /><file name="th-no-10-55px.jpg" server="ftp.mattblair.co.uk" local="3369898080" remote="3505243080" Dst="-1" /><file name="th-nurse-wo399.jpg" server="ftp.mattblair.co.uk" local="3403164566" remote="3505243080" Dst="-1" /><file name="th-oliver.jpg" server="ftp.mattblair.co.uk" local="3390372922" remote="3505243080" Dst="-1" /><file name="th-olympic-record.gif" server="ftp.mattblair.co.uk" local="3419857550" remote="3505243080" Dst="-1" /><file name="th-open-book.jpg" server="ftp.mattblair.co.uk" local="3385986690" remote="3505243080" Dst="-1" /><file name="th-open-data-55px.jpg" server="ftp.mattblair.co.uk" local="3377165818" remote="3505243080" Dst="-1" /><file name="th-opening-archives-2012.jpg" server="ftp.mattblair.co.uk" local="3406802434" remote="3505243080" Dst="-1" /><file name="th-organisation-chart.jpg" server="ftp.mattblair.co.uk" local="3390564054" remote="3505243080" Dst="-1" /><file name="th-pakistan-floods-55px.jpg" server="ftp.mattblair.co.uk" local="3365492088" remote="3505243080" Dst="-1" /><file name="th-parking-55px.jpg" server="ftp.mattblair.co.uk" local="3351758908" remote="3505243080" Dst="-1" /><file name="th-our-public-services.jpg" server="ftp.mattblair.co.uk" local="3383299610" remote="3505243080" Dst="-1" /><file name="th-parting-shots-55px.jpg" server="ftp.mattblair.co.uk" local="3369308292" remote="3505243080" Dst="-1" /><file name="th-peta-the-home-office-cat.jpg" server="ftp.mattblair.co.uk" local="3381215330" remote="3505243080" Dst="-1" /><file name="th-poorlife-55px.jpg" server="ftp.mattblair.co.uk" local="3364990702" remote="3505243080" Dst="-1" /><file name="th-pocket-maps-from-early-1900.jpg" server="ftp.mattblair.co.uk" local="3440588948" remote="3505243080" Dst="-1" /><file name="th-prem-19-282-8-detail.jpg" server="ftp.mattblair.co.uk" local="3376469890" remote="3505243080" Dst="-1" /><file name="th-pronom-data-tube.jpg" server="ftp.mattblair.co.uk" local="3393502994" remote="3505243080" Dst="-1" /><file name="th-psi-report-2010.jpg" server="ftp.mattblair.co.uk" local="3384850920" remote="3505243080" Dst="-1" /><file name="th-pubs-55px.jpg" server="ftp.mattblair.co.uk" local="3346156964" remote="3505243080" Dst="-1" /><file name="th-qr-code.jpg" server="ftp.mattblair.co.uk" local="3398944306" remote="3505243080" Dst="-1" /><file name="th-queens-award.jpg" server="ftp.mattblair.co.uk" local="3386152498" remote="3505243080" Dst="-1" /><file name="th-rail-1014-19-3-2.jpg" server="ftp.mattblair.co.uk" local="3395209546" remote="3505243080" Dst="-1" /><file name="th-rail-253-516-d.jpg" server="ftp.mattblair.co.uk" local="3400566010" remote="3505243080" Dst="-1" /><file name="th-record-copying-55px.jpg" server="ftp.mattblair.co.uk" local="3351758966" remote="3505243080" Dst="-1" /><file name="th-records-collections.jpg" server="ftp.mattblair.co.uk" local="3426745498" remote="3505243080" Dst="-1" /><file name="th-religiousarchives-55px.jpg" server="ftp.mattblair.co.uk" local="3373459204" remote="3505243080" Dst="-1" /><file name="th-research-guides-55px.jpg" server="ftp.mattblair.co.uk" local="3369741130" remote="3505243080" Dst="-1" /><file name="th-review-55px.jpg" server="ftp.mattblair.co.uk" local="3370423792" remote="3505243080" Dst="-1" /><file name="th-sachets-of-powder-found-in-file.jpg" server="ftp.mattblair.co.uk" local="3407140688" remote="3505243080" Dst="-1" /><file name="th-royal-navy-55px.jpg" server="ftp.mattblair.co.uk" local="3345805504" remote="3505243080" Dst="-1" /><file name="th-sandford-55px.jpg" server="ftp.mattblair.co.uk" local="3349181304" remote="3505243080" Dst="-1" /><file name="th-screenshot-bomb-sight.jpg" server="ftp.mattblair.co.uk" local="3437742314" remote="3505243080" Dst="-1" /><file name="th-seals-55px.jpg" server="ftp.mattblair.co.uk" local="3374739810" remote="3505243080" Dst="-1" /><file name="th-securityservice-2.jpg" server="ftp.mattblair.co.uk" local="3384502884" remote="3505243080" Dst="-1" /><file name="th-shropshire-map.jpg" server="ftp.mattblair.co.uk" local="3383221366" remote="3505243080" Dst="-1" /><file name="th-sneezes-55px.jpg" server="ftp.mattblair.co.uk" local="3343139832" remote="3505243080" Dst="-1" /><file name="th-soviet-55px.jpg" server="ftp.mattblair.co.uk" local="3362121008" remote="3505243080" Dst="-1" /><file name="th-sp-25-15.jpg" server="ftp.mattblair.co.uk" local="3406892168" remote="3505243080" Dst="-1" /><file name="th-spanish-war.jpg" server="ftp.mattblair.co.uk" local="3392034962" remote="3505243080" Dst="-1" /><file name="th-start-here.jpg" server="ftp.mattblair.co.uk" local="3440766274" remote="3505243080" Dst="-1" /><file name="th-stationery-office-55px.jpg" server="ftp.mattblair.co.uk" local="3374213702" remote="3505243080" Dst="-1" /><file name="th-survey-55px.gif" server="ftp.mattblair.co.uk" local="3318944930" remote="3505243080" Dst="-1" /><file name="th-state-papers-online-screenshot.jpg" server="ftp.mattblair.co.uk" local="3390371122" remote="3505243080" Dst="-1" /><file name="th-survey-55px_rdax.jpg" server="ftp.mattblair.co.uk" local="3348543636" remote="3505243080" Dst="-1" /><file name="th-survey-orange.jpg" server="ftp.mattblair.co.uk" local="3392196864" remote="3505243080" Dst="-1" /><file name="th-tal-americas.gif" server="ftp.mattblair.co.uk" local="3425964436" remote="3505243080" Dst="-1" /><file name="th-the-citizens-atlas-british-empire-1912.jpg" server="ftp.mattblair.co.uk" local="3436958896" remote="3505243080" Dst="-1" /><file name="th-titanic-2012-banner.jpg" server="ftp.mattblair.co.uk" local="3398686698" remote="3505243080" Dst="-1" /><file name="th-thatcher-extract-prem-19-5.jpg" server="ftp.mattblair.co.uk" local="3372919004" remote="3505243080" Dst="-1" /><file name="th-tithe-map-droylsden-nr-manchester-ir-30-18-106.jpg" server="ftp.mattblair.co.uk" local="3441095374" remote="3505243080" Dst="-1" /><file name="th-tna-logo-55px.jpg" server="ftp.mattblair.co.uk" local="3343386244" remote="3505243080" Dst="-1" /><file name="th-tna-porch.jpg" server="ftp.mattblair.co.uk" local="3392800772" remote="3505243080" Dst="-1" /><file name="th-top-secret-hw-80-4.jpg" server="ftp.mattblair.co.uk" local="3360582188" remote="3505243080" Dst="-1" /><file name="th-topsecret-hw-80-4.jpg" server="ftp.mattblair.co.uk" local="3360209266" remote="3505243080" Dst="-1" /><file name="th-twitter-55px.jpg" server="ftp.mattblair.co.uk" local="3346755888" remote="3505243080" Dst="-1" /><file name="th-uag.jpg" server="ftp.mattblair.co.uk" local="3433479760" remote="3505243080" Dst="-1" /><file name="th-ufo-aug-2011.jpg" server="ftp.mattblair.co.uk" local="3395821482" remote="3505243080" Dst="-1" /><file name="th-ufo-light.jpg" server="ftp.mattblair.co.uk" local="3381817504" remote="3505243080" Dst="-1" /><file name="th-ufo.jpg" server="ftp.mattblair.co.uk" local="3349262956" remote="3505243080" Dst="-1" /><file name="th-user-advisory-group.jpg" server="ftp.mattblair.co.uk" local="3387264976" remote="3505243080" Dst="-1" /><file name="th-valentine.jpg" server="ftp.mattblair.co.uk" local="3380532332" remote="3505243080" Dst="-1" /><file name="th-valentines-55px.jpg" server="ftp.mattblair.co.uk" local="3348752172" remote="3505243080" Dst="-1" /><file name="th-victorian-prison-ship-55px.jpg" server="ftp.mattblair.co.uk" local="3367393618" remote="3505243080" Dst="-1" /><file name="th-virgin-55px.jpg" server="ftp.mattblair.co.uk" local="3350043548" remote="3505243080" Dst="-1" /><file name="th-wdytya-55px.jpg" server="ftp.mattblair.co.uk" local="3344328846" remote="3505243080" Dst="-1" /><file name="th-vol-award-2012.jpg" server="ftp.mattblair.co.uk" local="3427976132" remote="3505243080" Dst="-1" /><file name="th-w-wallace-image-dol.jpg" server="ftp.mattblair.co.uk" local="3383051928" remote="3505243080" Dst="-1" /><file name="th-wdytya2013.jpg" server="ftp.mattblair.co.uk" local="3439988582" remote="3505243080" Dst="-1" /><file name="th-web-archive-55px.jpg" server="ftp.mattblair.co.uk" local="3352199134" remote="3505243080" Dst="-1" /><file name="th-wdytya-tree.jpg" server="ftp.mattblair.co.uk" local="3380088444" remote="3505243080" Dst="-1" /><file name="th-winds-55px.jpg" server="ftp.mattblair.co.uk" local="3347952028" remote="3505243080" Dst="-1" /><file name="th-womens-land-army.jpg" server="ftp.mattblair.co.uk" local="3381215400" remote="3505243080" Dst="-1" /><file name="th-web-archive.jpg" server="ftp.mattblair.co.uk" local="3393244822" remote="3505243080" Dst="-1" /><file name="th-writer-of-the-month.jpg" server="ftp.mattblair.co.uk" local="3436790010" remote="3505243080" Dst="-1" /><file name="th-working-in-the-archives.jpg" server="ftp.mattblair.co.uk" local="3403604746" remote="3505243080" Dst="-1" /><file name="theducationaward55px.jpg" server="ftp.mattblair.co.uk" local="3374214018" remote="3505243080" Dst="-1" /><file name="thumb-bt-archive.jpg" server="ftp.mattblair.co.uk" local="3409125904" remote="3505243080" Dst="-1" /><file name="thumb-mh47.jpg" server="ftp.mattblair.co.uk" local="3434092980" remote="3505243080" Dst="-1" /><file name="thumb-mi5-oct-2012.jpg" server="ftp.mattblair.co.uk" local="3434005822" remote="3505243080" Dst="-1" /><file name="thumb-olympic-discovery.jpg" server="ftp.mattblair.co.uk" local="3457437660" remote="3505243080" Dst="-1" /><file name="thumb-oil-paintings.jpg" server="ftp.mattblair.co.uk" local="3438328130" remote="3505243080" Dst="-1" /><file name="thumb-musuem.jpg" server="ftp.mattblair.co.uk" local="3437399516" remote="3505243080" Dst="-1" /><file name="thumb-oua.jpg" server="ftp.mattblair.co.uk" local="3436432052" remote="3505243080" Dst="-1" /><file name="thumb-scot-ref.jpg" server="ftp.mattblair.co.uk" local="3434368046" remote="3505243080" Dst="-1" /><file name="titanic-2012-banner.jpg" server="ftp.mattblair.co.uk" local="3398670898" remote="3505243080" Dst="-1" /><file name="tna-exterior-th.jpg" server="ftp.mattblair.co.uk" local="3368783080" remote="3505243080" Dst="-1" /><file name="tna-external-th.jpg" server="ftp.mattblair.co.uk" local="3343912966" remote="3505243080" Dst="-1" /><file name="uk-gov-licence-large-banner-th.jpg" server="ftp.mattblair.co.uk" local="3368614544" remote="3505243080" Dst="-1" /><file name="web-archive-th.jpg" server="ftp.mattblair.co.uk" local="3351761238" remote="3505243080" Dst="-1" /><file name="work25-208-3d-theatre-th.jpg" server="ftp.mattblair.co.uk" local="3343913032" remote="3505243080" Dst="-1" /><file name="Thumbs.db" server="ftp.mattblair.co.uk" local="3474892612" remote="3505243080" Dst="-1" /><file name="writer-thumb.jpg" server="ftp.mattblair.co.uk" local="3441350538" remote="3505243080" Dst="-1" /><file name="xxx-blog-bg.jpg" server="ftp.mattblair.co.uk" local="3462100722" remote="3505243080" Dst="-1" /><file name="xxx-media-bg.jpg" server="ftp.mattblair.co.uk" local="3462090548" remote="3505243080" Dst="-1" /></dwsync>